rockai/.DS_Store
rockai/__init__.py
rockai/command/__init__.py
rockai/command/openapi_schema.py
rockai/data_class.py
rockai/docker/__init__.py
rockai/docker/docker_util.py
rockai/docker/tf_compat.json
rockai/docker/torch_compat.json
rockai/docker/torch_version.py
rockai/example/.DS_Store
rockai/example/dockerignore
rockai/example/predictor.py
rockai/example/rock.yaml
rockai/parser/__init__.py
rockai/parser/config_util.py
rockai/predictor.py
rockai/rock.py
rockai/server/__init__.py
rockai/server/auth.py
rockai/server/files.py
rockai/server/http.py
rockai/server/json.py
rockai/server/log_handler.py
rockai/server/runner.py
rockai/server/types.py
rockai/server/utils.py
rockai/test.py
rockai-0.1.74.dist-info/LICENSE
rockai-0.1.74.dist-info/METADATA
rockai-0.1.74.dist-info/WHEEL
rockai-0.1.74.dist-info/entry_points.txt
rockai-0.1.74.dist-info/RECORD
